webullsdkcore/__init__.py
webullsdkcore/client.py
webullsdkcore/compat.py
webullsdkcore/headers.py
webullsdkcore/request.py
webullsdkcore/auth/__init__.py
webullsdkcore/auth/credentials.py
webullsdkcore/auth/algorithm/__init__.py
webullsdkcore/auth/algorithm/sha_hmac1.py
webullsdkcore/auth/algorithm/sha_hmac256.py
webullsdkcore/auth/composer/__init__.py
webullsdkcore/auth/composer/default_signature_composer.py
webullsdkcore/auth/signers/__init__.py
webullsdkcore/auth/signers/app_key_signer.py
webullsdkcore/auth/signers/signer.py
webullsdkcore/auth/signers/signer_factory.py
webullsdkcore/cache/__init__.py
webullsdkcore/common/__init__.py
webullsdkcore/common/api_type.py
webullsdkcore/common/easy_enum.py
webullsdkcore/common/region.py
webullsdkcore/context/__init__.py
webullsdkcore/context/request_context_holder.py
webullsdkcore/data/endpoints.json
webullsdkcore/data/retry_config.json
webullsdkcore/endpoint/__init__.py
webullsdkcore/endpoint/chained_endpoint_resolver.py
webullsdkcore/endpoint/default_endpoint_resolver.py
webullsdkcore/endpoint/local_config_regional_endpoint_resolver.py
webullsdkcore/endpoint/resolver_endpoint_request.py
webullsdkcore/endpoint/user_customized_endpoint_resolver.py
webullsdkcore/exception/__init__.py
webullsdkcore/exception/error_code.py
webullsdkcore/exception/error_msg.py
webullsdkcore/exception/exceptions.py
webullsdkcore/http/__init__.py
webullsdkcore/http/method_type.py
webullsdkcore/http/protocol_type.py
webullsdkcore/http/request.py
webullsdkcore/http/response.py
webullsdkcore/retry/__init__.py
webullsdkcore/retry/backoff_strategy.py
webullsdkcore/retry/retry_condition.py
webullsdkcore/retry/retry_policy.py
webullsdkcore/retry/retry_policy_context.py
webullsdkcore/utils/__init__.py
webullsdkcore/utils/common.py
webullsdkcore/utils/data.py
webullsdkcore/utils/validation.py
webullsdkcore/vendored/__init__.py
webullsdkcore/vendored/six.py
webullsdkcore/vendored/requests/__init__.py
webullsdkcore/vendored/requests/__version__.py
webull_python_sdk_core-0.1.18.dist-info/METADATA
webull_python_sdk_core-0.1.18.dist-info/WHEEL
webull_python_sdk_core-0.1.18.dist-info/top_level.txt
webull_python_sdk_core-0.1.18.dist-info/RECORD
